<?xml version="1.0" encoding="UTF-8" standalone="yes"?>
<executionprofile name="Generated">
    <description>Generated Profile</description>
    <workflows>
        <workflow name="all">
            <jobs>
                <job name="TmpltBank">
                    <count>30445</count>
                    <runtime>
                        <mean>18.45</mean>
                        <var>0.0</var>
                        <max>18.45</max>
                        <min>18.45</min>
                    </runtime>
                    <inputs>
                        <mean>4.053019E7</mean>
                        <var>0.0</var>
                        <max>4.053019E7</max>
                        <min>4.053019E7</min>
                    </inputs>
                    <outputs>
                        <mean>999134.0</mean>
                        <var>0.0</var>
                        <max>999134.0</max>
                        <min>999134.0</min>
                    </outputs>
                </job>
                <job name="mImgTbl">
                    <count>5050</count>
                    <runtime>
                        <mean>2.24</mean>
                        <var>0.0</var>
                        <max>2.24</max>
                        <min>2.24</min>
                    </runtime>
                    <inputs>
                        <mean>4.1649979E7</mean>
                        <var>0.0</var>
                        <max>4.1649979E7</max>
                        <min>4.1649979E7</min>
                    </inputs>
                    <outputs>
                        <mean>1995.0</mean>
                        <var>0.0</var>
                        <max>1995.0</max>
                        <min>1995.0</min>
                    </outputs>
                </job>
                <job name="Blast_synteny">
                    <count>5050</count>
                    <runtime>
                        <mean>33.0</mean>
                        <var>0.0</var>
                        <max>33.0</max>
                        <min>33.0</min>
                    </runtime>
                    <inputs>
                        <mean>3618694.0</mean>
                        <var>0.0</var>
                        <max>3618694.0</max>
                        <min>3618694.0</min>
                    </inputs>
                    <outputs>
                        <mean>1280864.0</mean>
                        <var>0.0</var>
                        <max>1280864.0</max>
                        <min>1280864.0</min>
                    </outputs>
                </job>
                <job name="filterContams_chr21">
                    <count>25250</count>
                    <runtime>
                        <mean>10.09</mean>
                        <var>0.0</var>
                        <max>10.09</max>
                        <min>10.09</min>
                    </runtime>
                    <inputs>
                        <mean>8.4006452E7</mean>
                        <var>0.0</var>
                        <max>8.4006452E7</max>
                        <min>8.4006452E7</min>
                    </inputs>
                    <outputs>
                        <mean>8.4006452E7</mean>
                        <var>0.0</var>
                        <max>8.4006452E7</max>
                        <min>8.4006452E7</min>
                    </outputs>
                </job>
                <job name="Transterm">
                    <count>5050</count>
                    <runtime>
                        <mean>68.0387</mean>
                        <var>0.0</var>
                        <max>68.0387</max>
                        <min>68.0387</min>
                    </runtime>
                    <inputs>
                        <mean>6367064.0</mean>
                        <var>0.0</var>
                        <max>6367064.0</max>
                        <min>6367064.0</min>
                    </inputs>
                    <outputs>
                        <mean>449409.0</mean>
                        <var>0.0</var>
                        <max>449409.0</max>
                        <min>449409.0</min>
                    </outputs>
                </job>
                <job name="FFN_Parse">
                    <count>5050</count>
                    <runtime>
                        <mean>1.8054</mean>
                        <var>0.0</var>
                        <max>1.8054</max>
                        <min>1.8054</min>
                    </runtime>
                    <inputs>
                        <mean>4967003.0</mean>
                        <var>0.0</var>
                        <max>4967003.0</max>
                        <min>4967003.0</min>
                    </inputs>
                    <outputs>
                        <mean>932400.0</mean>
                        <var>0.0</var>
                        <max>932400.0</max>
                        <min>932400.0</min>
                    </outputs>
                </job>
                <job name="SeismogramSynthesis">
                    <count>65650</count>
                    <runtime>
                        <mean>53.89</mean>
                        <var>0.0</var>
                        <max>53.89</max>
                        <min>53.89</min>
                    </runtime>
                    <inputs>
                        <mean>5.73883876E8</mean>
                        <var>0.0</var>
                        <max>5.73883876E8</max>
                        <min>5.73883876E8</min>
                    </inputs>
                    <outputs>
                        <mean>24000.0</mean>
                        <var>0.0</var>
                        <max>24000.0</max>
                        <min>24000.0</min>
                    </outputs>
                </job>
                <job name="Blast_QRNA">
                    <count>5050</count>
                    <runtime>
                        <mean>1471.1514</mean>
                        <var>0.0</var>
                        <max>1471.1514</max>
                        <min>1471.1514</min>
                    </runtime>
                    <inputs>
                        <mean>2.66493753E8</mean>
                        <var>0.0</var>
                        <max>2.66493753E8</max>
                        <min>2.66493753E8</min>
                    </inputs>
                    <outputs>
                        <mean>4609332.0</mean>
                        <var>0.0</var>
                        <max>4609332.0</max>
                        <min>4609332.0</min>
                    </outputs>
                </job>
                <job name="mAdd">
                    <count>5050</count>
                    <runtime>
                        <mean>3.03</mean>
                        <var>0.0</var>
                        <max>3.03</max>
                        <min>3.03</min>
                    </runtime>
                    <inputs>
                        <mean>2299.0</mean>
                        <var>0.0</var>
                        <max>2299.0</max>
                        <min>2299.0</min>
                    </inputs>
                    <outputs>
                        <mean>1.08862536E8</mean>
                        <var>0.0</var>
                        <max>1.08862536E8</max>
                        <min>1.08862536E8</min>
                    </outputs>
                </job>
                <job name="RNAMotif">
                    <count>5050</count>
                    <runtime>
                        <mean>41.3993</mean>
                        <var>0.0</var>
                        <max>41.3993</max>
                        <min>41.3993</min>
                    </runtime>
                    <inputs>
                        <mean>6003915.0</mean>
                        <var>0.0</var>
                        <max>6003915.0</max>
                        <min>6003915.0</min>
                    </inputs>
                    <outputs>
                        <mean>1097926.0</mean>
                        <var>0.0</var>
                        <max>1097926.0</max>
                        <min>1097926.0</min>
                    </outputs>
                </job>
                <job name="Inspiral">
                    <count>67542</count>
                    <runtime>
                        <mean>561.02</mean>
                        <var>0.0</var>
                        <max>561.02</max>
                        <min>561.02</min>
                    </runtime>
                    <inputs>
                        <mean>4.3916065E7</mean>
                        <var>0.0</var>
                        <max>4.3916065E7</max>
                        <min>4.3916065E7</min>
                    </inputs>
                    <outputs>
                        <mean>385816.0</mean>
                        <var>0.0</var>
                        <max>385816.0</max>
                        <min>385816.0</min>
                    </outputs>
                </job>
                <job name="mConcatFit">
                    <count>5050</count>
                    <runtime>
                        <mean>0.72</mean>
                        <var>0.0</var>
                        <max>0.72</max>
                        <min>0.72</min>
                    </runtime>
                    <inputs>
                        <mean>2709092.0</mean>
                        <var>0.0</var>
                        <max>2709092.0</max>
                        <min>2709092.0</min>
                    </inputs>
                    <outputs>
                        <mean>1889.0</mean>
                        <var>0.0</var>
                        <max>1889.0</max>
                        <min>1889.0</min>
                    </outputs>
                </job>
                <job name="Blast">
                    <count>5050</count>
                    <runtime>
                        <mean>2896.2004</mean>
                        <var>0.0</var>
                        <max>2896.2004</max>
                        <min>2896.2004</min>
                    </runtime>
                    <inputs>
                        <mean>2.63019736E8</mean>
                        <var>0.0</var>
                        <max>2.63019736E8</max>
                        <min>2.63019736E8</min>
                    </inputs>
                    <outputs>
                        <mean>6437575.0</mean>
                        <var>0.0</var>
                        <max>6437575.0</max>
                        <min>6437575.0</min>
                    </outputs>
                </job>
                <job name="mProjectPP">
                    <count>25250</count>
                    <runtime>
                        <mean>13.77</mean>
                        <var>0.0</var>
                        <max>13.77</max>
                        <min>13.77</min>
                    </runtime>
                    <inputs>
                        <mean>4222384.0</mean>
                        <var>0.0</var>
                        <max>4222384.0</max>
                        <min>4222384.0</min>
                    </inputs>
                    <outputs>
                        <mean>8338976.0</mean>
                        <var>0.0</var>
                        <max>8338976.0</max>
                        <min>8338976.0</min>
                    </outputs>
                </job>
                <job name="mShrink">
                    <count>5050</count>
                    <runtime>
                        <mean>3.86</mean>
                        <var>0.0</var>
                        <max>3.86</max>
                        <min>3.86</min>
                    </runtime>
                    <inputs>
                        <mean>1.08862536E8</mean>
                        <var>0.0</var>
                        <max>1.08862536E8</max>
                        <min>1.08862536E8</min>
                    </inputs>
                    <outputs>
                        <mean>2178121.0</mean>
                        <var>0.0</var>
                        <max>2178121.0</max>
                        <min>2178121.0</min>
                    </outputs>
                </job>
                <job name="mapMerge_chr21">
                    <count>5050</count>
                    <runtime>
                        <mean>18.91</mean>
                        <var>0.0</var>
                        <max>18.91</max>
                        <min>18.91</min>
                    </runtime>
                    <inputs>
                        <mean>4.0216155E7</mean>
                        <var>0.0</var>
                        <max>4.0216155E7</max>
                        <min>4.0216155E7</min>
                    </inputs>
                    <outputs>
                        <mean>3.9939917E7</mean>
                        <var>0.0</var>
                        <max>3.9939917E7</max>
                        <min>3.9939917E7</min>
                    </outputs>
                </job>
                <job name="Blast_candidate">
                    <count>5050</count>
                    <runtime>
                        <mean>5.9441</mean>
                        <var>0.0</var>
                        <max>5.9441</max>
                        <min>5.9441</min>
                    </runtime>
                    <inputs>
                        <mean>1438257.0</mean>
                        <var>0.0</var>
                        <max>1438257.0</max>
                        <min>1438257.0</min>
                    </inputs>
                    <outputs>
                        <mean>16976.0</mean>
                        <var>0.0</var>
                        <max>16976.0</max>
                        <min>16976.0</min>
                    </outputs>
                </job>
                <job name="Thinca">
                    <count>16416</count>
                    <runtime>
                        <mean>5.54</mean>
                        <var>0.0</var>
                        <max>5.54</max>
                        <min>5.54</min>
                    </runtime>
                    <inputs>
                        <mean>1821210.0</mean>
                        <var>0.0</var>
                        <max>1821210.0</max>
                        <min>1821210.0</min>
                    </inputs>
                    <outputs>
                        <mean>42989.0</mean>
                        <var>0.0</var>
                        <max>42989.0</max>
                        <min>42989.0</min>
                    </outputs>
                </job>
                <job name="mBgModel">
                    <count>5050</count>
                    <runtime>
                        <mean>1.52</mean>
                        <var>0.0</var>
                        <max>1.52</max>
                        <min>1.52</min>
                    </runtime>
                    <inputs>
                        <mean>2726.0</mean>
                        <var>0.0</var>
                        <max>2726.0</max>
                        <min>2726.0</min>
                    </inputs>
                    <outputs>
                        <mean>265.0</mean>
                        <var>0.0</var>
                        <max>265.0</max>
                        <min>265.0</min>
                    </outputs>
                </job>
                <job name="maqindex_chr21">
                    <count>5050</count>
                    <runtime>
                        <mean>0.05</mean>
                        <var>0.0</var>
                        <max>0.05</max>
                        <min>0.05</min>
                    </runtime>
                    <inputs>
                        <mean>3.7939768E7</mean>
                        <var>0.0</var>
                        <max>3.7939768E7</max>
                        <min>3.7939768E7</min>
                    </inputs>
                    <outputs>
                        <mean>763760.0</mean>
                        <var>0.0</var>
                        <max>763760.0</max>
                        <min>763760.0</min>
                    </outputs>
                </job>
                <job name="fastq2bfq_chr21">
                    <count>25250</count>
                    <runtime>
                        <mean>4.77</mean>
                        <var>0.0</var>
                        <max>4.77</max>
                        <min>4.77</min>
                    </runtime>
                    <inputs>
                        <mean>3.1868462E7</mean>
                        <var>0.0</var>
                        <max>3.1868462E7</max>
                        <min>3.1868462E7</min>
                    </inputs>
                    <outputs>
                        <mean>7766460.0</mean>
                        <var>0.0</var>
                        <max>7766460.0</max>
                        <min>7766460.0</min>
                    </outputs>
                </job>
                <job name="mDiffFit">
                    <count>45450</count>
                    <runtime>
                        <mean>10.65</mean>
                        <var>0.0</var>
                        <max>10.65</max>
                        <min>10.65</min>
                    </runtime>
                    <inputs>
                        <mean>1.6665578E7</mean>
                        <var>0.0</var>
                        <max>1.6665578E7</max>
                        <min>1.6665578E7</min>
                    </inputs>
                    <outputs>
                        <mean>344265.0</mean>
                        <var>0.0</var>
                        <max>344265.0</max>
                        <min>344265.0</min>
                    </outputs>
                </job>
                <job name="Blast_paralogues">
                    <count>5050</count>
                    <runtime>
                        <mean>5.8325</mean>
                        <var>0.0</var>
                        <max>5.8325</max>
                        <min>5.8325</min>
                    </runtime>
                    <inputs>
                        <mean>1265397.0</mean>
                        <var>0.0</var>
                        <max>1265397.0</max>
                        <min>1265397.0</min>
                    </inputs>
                    <outputs>
                        <mean>863443.0</mean>
                        <var>0.0</var>
                        <max>863443.0</max>
                        <min>863443.0</min>
                    </outputs>
                </job>
                <job name="pileup_chr21">
                    <count>5050</count>
                    <runtime>
                        <mean>5153.71</mean>
                        <var>0.0</var>
                        <max>5153.71</max>
                        <min>5153.71</min>
                    </runtime>
                    <inputs>
                        <mean>4.548547215E9</mean>
                        <var>0.0</var>
                        <max>4.548547215E9</max>
                        <min>4.548547215E9</min>
                    </inputs>
                    <outputs>
                        <mean>4166310.0</mean>
                        <var>0.0</var>
                        <max>4166310.0</max>
                        <min>4166310.0</min>
                    </outputs>
                </job>
                <job name="ExtractSGT">
                    <count>10100</count>
                    <runtime>
                        <mean>159.8</mean>
                        <var>0.0</var>
                        <max>159.8</max>
                        <min>159.8</min>
                    </runtime>
                    <inputs>
                        <mean>4.0393803556E10</mean>
                        <var>0.0</var>
                        <max>4.0393803556E10</max>
                        <min>4.0393803556E10</min>
                    </inputs>
                    <outputs>
                        <mean>5.47510336E8</mean>
                        <var>0.0</var>
                        <max>5.47510336E8</max>
                        <min>5.47510336E8</min>
                    </outputs>
                </job>
                <job name="map_chr21">
                    <count>25250</count>
                    <runtime>
                        <mean>11655.16</mean>
                        <var>0.0</var>
                        <max>11655.16</max>
                        <min>11655.16</min>
                    </runtime>
                    <inputs>
                        <mean>4.557296533E9</mean>
                        <var>0.0</var>
                        <max>4.557296533E9</max>
                        <min>4.557296533E9</min>
                    </inputs>
                    <outputs>
                        <mean>8441804.0</mean>
                        <var>0.0</var>
                        <max>8441804.0</max>
                        <min>8441804.0</min>
                    </outputs>
                </job>
                <job name="Findterm">
                    <count>5050</count>
                    <runtime>
                        <mean>1536.0977</mean>
                        <var>0.0</var>
                        <max>1536.0977</max>
                        <min>1536.0977</min>
                    </runtime>
                    <inputs>
                        <mean>6578231.0</mean>
                        <var>0.0</var>
                        <max>6578231.0</max>
                        <min>6578231.0</min>
                    </inputs>
                    <outputs>
                        <mean>3.8814815E7</mean>
                        <var>0.0</var>
                        <max>3.8814815E7</max>
                        <min>3.8814815E7</min>
                    </outputs>
                </job>
                <job name="Patser">
                    <count>85850</count>
                    <runtime>
                        <mean>1.4763</mean>
                        <var>0.0</var>
                        <max>1.4763</max>
                        <min>1.4763</min>
                    </runtime>
                    <inputs>
                        <mean>6157236.0</mean>
                        <var>0.0</var>
                        <max>6157236.0</max>
                        <min>6157236.0</min>
                    </inputs>
                    <outputs>
                        <mean>113295.0</mean>
                        <var>0.0</var>
                        <max>113295.0</max>
                        <min>113295.0</min>
                    </outputs>
                </job>
                <job name="PeakValCalcOkaya">
                    <count>65650</count>
                    <runtime>
                        <mean>1.37</mean>
                        <var>0.0</var>
                        <max>1.37</max>
                        <min>1.37</min>
                    </runtime>
                    <inputs>
                        <mean>24000.0</mean>
                        <var>0.0</var>
                        <max>24000.0</max>
                        <min>24000.0</min>
                    </inputs>
                    <outputs>
                        <mean>216.0</mean>
                        <var>0.0</var>
                        <max>216.0</max>
                        <min>216.0</min>
                    </outputs>
                </job>
                <job name="Patser_concate">
                    <count>5050</count>
                    <runtime>
                        <mean>0.0982</mean>
                        <var>0.0</var>
                        <max>0.0982</max>
                        <min>0.0982</min>
                    </runtime>
                    <inputs>
                        <mean>1627346.0</mean>
                        <var>0.0</var>
                        <max>1627346.0</max>
                        <min>1627346.0</min>
                    </inputs>
                    <outputs>
                        <mean>1627346.0</mean>
                        <var>0.0</var>
                        <max>1627346.0</max>
                        <min>1627346.0</min>
                    </outputs>
                </job>
                <job name="mBackground">
                    <count>25250</count>
                    <runtime>
                        <mean>10.86</mean>
                        <var>0.0</var>
                        <max>10.86</max>
                        <min>10.86</min>
                    </runtime>
                    <inputs>
                        <mean>8340125.0</mean>
                        <var>0.0</var>
                        <max>8340125.0</max>
                        <min>8340125.0</min>
                    </inputs>
                    <outputs>
                        <mean>8339860.0</mean>
                        <var>0.0</var>
                        <max>8339860.0</max>
                        <min>8339860.0</min>
                    </outputs>
                </job>
                <job name="ZipPSA">
                    <count>5050</count>
                    <runtime>
                        <mean>0.18</mean>
                        <var>0.0</var>
                        <max>0.18</max>
                        <min>0.18</min>
                    </runtime>
                    <inputs>
                        <mean>0.0</mean>
                        <var>0.0</var>
                        <max>0.0</max>
                        <min>0.0</min>
                    </inputs>
                    <outputs>
                        <mean>495.0</mean>
                        <var>0.0</var>
                        <max>495.0</max>
                        <min>495.0</min>
                    </outputs>
                </job>
                <job name="ZipSeis">
                    <count>5050</count>
                    <runtime>
                        <mean>0.22</mean>
                        <var>0.0</var>
                        <max>0.22</max>
                        <min>0.22</min>
                    </runtime>
                    <inputs>
                        <mean>0.0</mean>
                        <var>0.0</var>
                        <max>0.0</max>
                        <min>0.0</min>
                    </inputs>
                    <outputs>
                        <mean>50855.0</mean>
                        <var>0.0</var>
                        <max>50855.0</max>
                        <min>50855.0</min>
                    </outputs>
                </job>
                <job name="fastqSplit_chr21">
                    <count>5050</count>
                    <runtime>
                        <mean>55.86</mean>
                        <var>0.0</var>
                        <max>55.86</max>
                        <min>55.86</min>
                    </runtime>
                    <inputs>
                        <mean>4.12651187E8</mean>
                        <var>0.0</var>
                        <max>4.12651187E8</max>
                        <min>4.12651187E8</min>
                    </inputs>
                    <outputs>
                        <mean>4.12651187E8</mean>
                        <var>0.0</var>
                        <max>4.12651187E8</max>
                        <min>4.12651187E8</min>
                    </outputs>
                </job>
                <job name="SRNA">
                    <count>5050</count>
                    <runtime>
                        <mean>441.1153</mean>
                        <var>0.0</var>
                        <max>441.1153</max>
                        <min>441.1153</min>
                    </runtime>
                    <inputs>
                        <mean>6.4587276E7</mean>
                        <var>0.0</var>
                        <max>6.4587276E7</max>
                        <min>6.4587276E7</min>
                    </inputs>
                    <outputs>
                        <mean>6738368.0</mean>
                        <var>0.0</var>
                        <max>6738368.0</max>
                        <min>6738368.0</min>
                    </outputs>
                </job>
                <job name="mJPEG">
                    <count>5050</count>
                    <runtime>
                        <mean>0.9</mean>
                        <var>0.0</var>
                        <max>0.9</max>
                        <min>0.9</min>
                    </runtime>
                    <inputs>
                        <mean>2178121.0</mean>
                        <var>0.0</var>
                        <max>2178121.0</max>
                        <min>2178121.0</min>
                    </inputs>
                    <outputs>
                        <mean>499222.0</mean>
                        <var>0.0</var>
                        <max>499222.0</max>
                        <min>499222.0</min>
                    </outputs>
                </job>
                <job name="sol2sanger_chr21">
                    <count>25250</count>
                    <runtime>
                        <mean>2.79</mean>
                        <var>0.0</var>
                        <max>2.79</max>
                        <min>2.79</min>
                    </runtime>
                    <inputs>
                        <mean>4.1529844E7</mean>
                        <var>0.0</var>
                        <max>4.1529844E7</max>
                        <min>4.1529844E7</min>
                    </inputs>
                    <outputs>
                        <mean>3.1868462E7</mean>
                        <var>0.0</var>
                        <max>3.1868462E7</max>
                        <min>3.1868462E7</min>
                    </outputs>
                </job>
                <job name="TrigBank">
                    <count>37097</count>
                    <runtime>
                        <mean>5.31</mean>
                        <var>0.0</var>
                        <max>5.31</max>
                        <min>5.31</min>
                    </runtime>
                    <inputs>
                        <mean>42668.0</mean>
                        <var>0.0</var>
                        <max>42668.0</max>
                        <min>42668.0</min>
                    </inputs>
                    <outputs>
                        <mean>16219.0</mean>
                        <var>0.0</var>
                        <max>16219.0</max>
                        <min>16219.0</min>
                    </outputs>
                </job>
                <job name="SRNA_annotate">
                    <count>5050</count>
                    <runtime>
                        <mean>2.063</mean>
                        <var>0.0</var>
                        <max>2.063</max>
                        <min>2.063</min>
                    </runtime>
                    <inputs>
                        <mean>4402201.0</mean>
                        <var>0.0</var>
                        <max>4402201.0</max>
                        <min>4402201.0</min>
                    </inputs>
                    <outputs>
                        <mean>1404407.0</mean>
                        <var>0.0</var>
                        <max>1404407.0</max>
                        <min>1404407.0</min>
                    </outputs>
                </job>
            </jobs>
        </workflow>
    </workflows>
</executionprofile>
